test_counter.v
module test_counter(input clk, input reset, output reg [7:0] counter);
  always @(posedge clk or posedge reset) begin
    if (reset)
      counter <= 0;
    else
      counter <= counter + 1;
  end
endmodule

tb_test_counter.v
`timescale 1ns/1ps
module tb_test_counter;
  reg clk;
  reg reset;
  wire [7:0] counter;

  test_counter uut (
    .clk (clk),
    .reset(reset),
    .counter(counter)
  );

  initial clk = 0;
  always #5 clk = ~clk;

  initial begin
    reset = 1;
    #20;
    reset = 0;
    #200;
    $finish;
  end

  initial begin
    $dumpfile("waveform.vcd");
    $dumpvars(0, tb_test_counter);
  end
endmodule

Experimentation/waveform.vcd
$date
	Tue Feb 04 16:31:25 2025
$end
$version
	Icarus Verilog
$end
$timescale
	1ps
$end
$scope module tb_test_counter $end
$var wire 8 ! counter [7:0] $end
$var reg 1 " clk $end
$var reg 1 # reset $end
$scope module uut $end
$var wire 1 " clk $end
$var wire 1 # reset $end
$var reg 8 $ counter [7:0] $end
$upscope $end
$upscope $end
$enddefinitions $end
$comment Show the parameter values. $end
$dumpall
$end
#0
$dumpvars
b0 $
1#
0"
b0 !
$end
#5000
1"
#10000
0"
#15000
1"
#20000
0"
0#
#25000
b1 !
b1 $
1"
#30000
0"
#35000
b10 !
b10 $
1"
#40000
0"
#45000
b11 !
b11 $
1"
#50000
0"
#55000
b100 !
b100 $
1"
#60000
0"
#65000
b101 !
b101 $
1"
#70000
0"
#75000
b110 !
b110 $
1"
#80000
0"
#85000
b111 !
b111 $
1"
#90000
0"
#95000
b1000 !
b1000 $
1"
#100000
0"
#105000
b1001 !
b1001 $
1"
#110000
0"
#115000
b1010 !
b1010 $
1"
#120000
0"
#125000
b1011 !
b1011 $
1"
#130000
0"
#135000
b1100 !
b1100 $
1"
#140000
0"
#145000
b1101 !
b1101 $
1"
#150000
0"
#155000
b1110 !
b1110 $
1"
#160000
0"
#165000
b1111 !
b1111 $
1"
#170000
0"
#175000
b10000 !
b10000 $
1"
#180000
0"
#185000
b10001 !
b10001 $
1"
#190000
0"
#195000
b10010 !
b10010 $
1"
#200000
0"
#205000
b10011 !
b10011 $
1"
#210000
0"
#215000
b10100 !
b10100 $
1"
